justobjects/__init__.py
justobjects/decorators.py
justobjects/py.typed
justobjects/schemas.py
justobjects/transforms.py
justobjects/types.py
justobjects/typings.py
justobjects/validation.py
justobjects/plugins/__init__.py
justobjects/plugins/jomypy.py
justobjects-0.3.0.dist-info/LICENSE
justobjects-0.3.0.dist-info/METADATA
justobjects-0.3.0.dist-info/WHEEL
justobjects-0.3.0.dist-info/top_level.txt
justobjects-0.3.0.dist-info/zip-safe
justobjects-0.3.0.dist-info/RECORD
