Metadata-Version: 2.1
Name: justobjects
Version: 0.3.0
Summary: Simple data object (de)serialization and validation
Home-page: https://justobjects.readthedocs.io
Author: Rowland Ogwara
Author-email: r.ogwara@gmail.com
License: Apache Software License 2.0
Project-URL: Source, https://github.com/kulgan/justobjects
Project-URL: Documentation, https://justobjects.readthedocs.io
Keywords: jsonschema,objects,just objects
Platform: UNKNOWN
Classifier: Development Status :: 3 - Alpha
Classifier: License :: OSI Approved :: Apache Software License
Classifier: Intended Audience :: Developers
Classifier: Programming Language :: Python
Classifier: Programming Language :: Python :: 3.6
Classifier: Programming Language :: Python :: 3.7
Classifier: Programming Language :: Python :: 3.8
Classifier: Programming Language :: Python :: 3.9
Classifier: Programming Language :: Python :: 3.10
Classifier: Operating System :: Unix
Classifier: Operating System :: POSIX :: Linux
Classifier: Topic :: Software Development :: Libraries :: Python Modules
Classifier: Topic :: Utilities
Requires-Python: >=3.6
License-File: LICENSE
Requires-Dist: attrs
Requires-Dist: jsonschema
Requires-Dist: validators
Requires-Dist: typing-extensions ; python_version < "3.8"
Provides-Extra: changelog
Requires-Dist: towncrier ; extra == 'changelog'
Provides-Extra: dev
Requires-Dist: coverage[toml] ; extra == 'dev'
Requires-Dist: pytest ; extra == 'dev'
Requires-Dist: pytest-cov ; extra == 'dev'
Provides-Extra: docs
Requires-Dist: sphinx ; extra == 'docs'
Requires-Dist: sphinx-rtd-theme ; extra == 'docs'
Requires-Dist: sphinxcontrib-napoleon ; extra == 'docs'
Provides-Extra: lint
Requires-Dist: mypy ; extra == 'lint'
Requires-Dist: pre-commit ; extra == 'lint'
